multistage_build/__init__.py
multistage_build/_build_backend.py
multistage_build/_version.py
multistage_build/tests/__init__.py
multistage_build/tests/test_build_backend.py
multistage_build/tests/test_multistage_build.py
multistage_build-0.1.0.dist-info/METADATA
multistage_build-0.1.0.dist-info/WHEEL
multistage_build-0.1.0.dist-info/top_level.txt
multistage_build-0.1.0.dist-info/RECORD
