Metadata-Version: 2.4
Name: multistage-build
Version: 0.1.0
Summary: A generic PEP-517 build backend which allows additional processing to be applied to the resulting metadata, wheel and/or editable wheel.
Author-email: Phil Elson <philip.elson@cern.ch>
Project-URL: Homepage, https://github.com/pelson/multistage-build
Project-URL: Repository, https://github.com/pelson/multistage-build
Classifier: Programming Language :: Python :: 3
Classifier: Operating System :: OS Independent
Requires-Python: >=3.7
Requires-Dist: importlib_metadata>=4.6; python_version < "3.10"
Requires-Dist: tomli>=1.1.0; python_version < "3.11"
Provides-Extra: test
Requires-Dist: build; extra == "test"
Requires-Dist: pytest; extra == "test"
Requires-Dist: pyproject_hooks; extra == "test"
Provides-Extra: doc
Provides-Extra: dev
Requires-Dist: multistage-build[doc,test]; extra == "dev"
